jellyfin_apiclient_python/__init__.py
jellyfin_apiclient_python/api.py
jellyfin_apiclient_python/client.py
jellyfin_apiclient_python/configuration.py
jellyfin_apiclient_python/connection_manager.py
jellyfin_apiclient_python/credentials.py
jellyfin_apiclient_python/exceptions.py
jellyfin_apiclient_python/http.py
jellyfin_apiclient_python/keepalive.py
jellyfin_apiclient_python/timesync_manager.py
jellyfin_apiclient_python/ws_client.py
jellyfin_apiclient_python-1.10.0.dist-info/LICENSE.md
jellyfin_apiclient_python-1.10.0.dist-info/METADATA
jellyfin_apiclient_python-1.10.0.dist-info/WHEEL
jellyfin_apiclient_python-1.10.0.dist-info/top_level.txt
jellyfin_apiclient_python-1.10.0.dist-info/RECORD
