Metadata-Version: 2.1
Name: jellyfin-apiclient-python
Version: 1.10.0
Summary: Python API client for Jellyfin
Author-email: Izzie Walton <izzie@iwalton.com>
License: ### GNU GENERAL PUBLIC LICENSE
Project-URL: Repository, https://github.com/iwalton3/jellyfin-apiclient-python
Classifier: Programming Language :: Python :: 3
Classifier: License :: OSI Approved :: GNU General Public License v3 (GPLv3)
Classifier: Operating System :: OS Independent
Requires-Python: >=3.6
License-File: LICENSE.md
Requires-Dist: requests
Requires-Dist: urllib3
Requires-Dist: websocket-client
Requires-Dist: certifi
